mcp_server_gad/__init__.py
mcp_server_gad/__main__.py
mcp_server_gad/server.py
mcp_server_gad-0.0.1.dist-info/METADATA
mcp_server_gad-0.0.1.dist-info/WHEEL
mcp_server_gad-0.0.1.dist-info/entry_points.txt
mcp_server_gad-0.0.1.dist-info/RECORD
