Metadata-Version: 2.4
Name: mcp-server-gad
Version: 0.0.1
Summary: A secure MCP server that provides a read-only PostgreSQL query tool for gad.
Requires-Python: >=3.10
Requires-Dist: mcp>=1.7.1
Requires-Dist: psycopg2-binary
Requires-Dist: sqlalchemy
